{
  "best_metric": null,
  "best_model_checkpoint": null,
  "epoch": 2.9965792474344357,
  "eval_steps": 500,
  "global_step": 657,
  "is_hyper_param_search": false,
  "is_local_process_zero": true,
  "is_world_process_zero": true,
  "log_history": [
    {
      "epoch": 0.04561003420752566,
      "grad_norm": 1.2836235761642456,
      "learning_rate": 7.5757575757575764e-06,
      "loss": 1.1344,
      "step": 10
    },
    {
      "epoch": 0.09122006841505131,
      "grad_norm": 0.43765372037887573,
      "learning_rate": 1.5151515151515153e-05,
      "loss": 0.4145,
      "step": 20
    },
    {
      "epoch": 0.13683010262257697,
      "grad_norm": 0.4320650100708008,
      "learning_rate": 2.272727272727273e-05,
      "loss": 0.2618,
      "step": 30
    },
    {
      "epoch": 0.18244013683010263,
      "grad_norm": 0.3681085407733917,
      "learning_rate": 3.0303030303030306e-05,
      "loss": 0.2075,
      "step": 40
    },
    {
      "epoch": 0.22805017103762829,
      "grad_norm": 0.28288742899894714,
      "learning_rate": 3.787878787878788e-05,
      "loss": 0.191,
      "step": 50
    },
    {
      "epoch": 0.27366020524515394,
      "grad_norm": 0.2754509449005127,
      "learning_rate": 4.545454545454546e-05,
      "loss": 0.1868,
      "step": 60
    },
    {
      "epoch": 0.31927023945267957,
      "grad_norm": 0.3722975552082062,
      "learning_rate": 4.999434882941783e-05,
      "loss": 0.1876,
      "step": 70
    },
    {
      "epoch": 0.36488027366020526,
      "grad_norm": 0.22634123265743256,
      "learning_rate": 4.993080249767159e-05,
      "loss": 0.1864,
      "step": 80
    },
    {
      "epoch": 0.4104903078677309,
      "grad_norm": 0.2596118152141571,
      "learning_rate": 4.979682598982912e-05,
      "loss": 0.1794,
      "step": 90
    },
    {
      "epoch": 0.45610034207525657,
      "grad_norm": 0.323424756526947,
      "learning_rate": 4.959279779306672e-05,
      "loss": 0.1711,
      "step": 100
    },
    {
      "epoch": 0.5017103762827823,
      "grad_norm": 0.27820077538490295,
      "learning_rate": 4.931929429243368e-05,
      "loss": 0.1871,
      "step": 110
    },
    {
      "epoch": 0.5473204104903079,
      "grad_norm": 0.16422025859355927,
      "learning_rate": 4.8977088142549285e-05,
      "loss": 0.17,
      "step": 120
    },
    {
      "epoch": 0.5929304446978335,
      "grad_norm": 0.18240845203399658,
      "learning_rate": 4.856714608483312e-05,
      "loss": 0.1775,
      "step": 130
    },
    {
      "epoch": 0.6385404789053591,
      "grad_norm": 0.1975230872631073,
      "learning_rate": 4.8090626216434944e-05,
      "loss": 0.1728,
      "step": 140
    },
    {
      "epoch": 0.6841505131128849,
      "grad_norm": 0.44317901134490967,
      "learning_rate": 4.754887471857969e-05,
      "loss": 0.1639,
      "step": 150
    },
    {
      "epoch": 0.7297605473204105,
      "grad_norm": 0.2942394018173218,
      "learning_rate": 4.694342205356988e-05,
      "loss": 0.1876,
      "step": 160
    },
    {
      "epoch": 0.7753705815279361,
      "grad_norm": 0.3128633201122284,
      "learning_rate": 4.627597864118919e-05,
      "loss": 0.1688,
      "step": 170
    },
    {
      "epoch": 0.8209806157354618,
      "grad_norm": 0.331701397895813,
      "learning_rate": 4.554843002672129e-05,
      "loss": 0.1709,
      "step": 180
    },
    {
      "epoch": 0.8665906499429875,
      "grad_norm": 0.2380143254995346,
      "learning_rate": 4.476283155423465e-05,
      "loss": 0.1584,
      "step": 190
    },
    {
      "epoch": 0.9122006841505131,
      "grad_norm": 0.2704833447933197,
      "learning_rate": 4.3921402560181175e-05,
      "loss": 0.1798,
      "step": 200
    },
    {
      "epoch": 0.9578107183580388,
      "grad_norm": 0.25977620482444763,
      "learning_rate": 4.302652010371205e-05,
      "loss": 0.1674,
      "step": 210
    },
    {
      "epoch": 1.0034207525655645,
      "grad_norm": 0.19989818334579468,
      "learning_rate": 4.208071225142282e-05,
      "loss": 0.1603,
      "step": 220
    },
    {
      "epoch": 1.0490307867730901,
      "grad_norm": 0.28224918246269226,
      "learning_rate": 4.108665093549844e-05,
      "loss": 0.1588,
      "step": 230
    },
    {
      "epoch": 1.0946408209806158,
      "grad_norm": 0.3209839165210724,
      "learning_rate": 4.0047144405434175e-05,
      "loss": 0.1529,
      "step": 240
    },
    {
      "epoch": 1.1402508551881414,
      "grad_norm": 0.20283570885658264,
      "learning_rate": 3.896512929465659e-05,
      "loss": 0.1511,
      "step": 250
    },
    {
      "epoch": 1.185860889395667,
      "grad_norm": 0.3035765588283539,
      "learning_rate": 3.7843662324456466e-05,
      "loss": 0.1582,
      "step": 260
    },
    {
      "epoch": 1.2314709236031927,
      "grad_norm": 0.38095682859420776,
      "learning_rate": 3.668591166867035e-05,
      "loss": 0.1645,
      "step": 270
    },
    {
      "epoch": 1.2770809578107183,
      "grad_norm": 0.3973912000656128,
      "learning_rate": 3.5495148003505717e-05,
      "loss": 0.163,
      "step": 280
    },
    {
      "epoch": 1.3226909920182441,
      "grad_norm": 0.2543030083179474,
      "learning_rate": 3.4274735267794245e-05,
      "loss": 0.1757,
      "step": 290
    },
    {
      "epoch": 1.3683010262257698,
      "grad_norm": 0.19665436446666718,
      "learning_rate": 3.3028121159775656e-05,
      "loss": 0.1458,
      "step": 300
    },
    {
      "epoch": 1.4139110604332954,
      "grad_norm": 0.5005244612693787,
      "learning_rate": 3.1758827397259074e-05,
      "loss": 0.1519,
      "step": 310
    },
    {
      "epoch": 1.459521094640821,
      "grad_norm": 0.23445643484592438,
      "learning_rate": 3.0470439768677116e-05,
      "loss": 0.144,
      "step": 320
    },
    {
      "epoch": 1.5051311288483467,
      "grad_norm": 0.24491700530052185,
      "learning_rate": 2.9166598003138766e-05,
      "loss": 0.1632,
      "step": 330
    },
    {
      "epoch": 1.5507411630558723,
      "grad_norm": 0.448991596698761,
      "learning_rate": 2.785098548809844e-05,
      "loss": 0.1456,
      "step": 340
    },
    {
      "epoch": 1.596351197263398,
      "grad_norm": 0.3246448338031769,
      "learning_rate": 2.652731886368906e-05,
      "loss": 0.1507,
      "step": 350
    },
    {
      "epoch": 1.6419612314709235,
      "grad_norm": 0.2045176476240158,
      "learning_rate": 2.5199337523115418e-05,
      "loss": 0.1543,
      "step": 360
    },
    {
      "epoch": 1.6875712656784492,
      "grad_norm": 0.1868995726108551,
      "learning_rate": 2.3870793048769537e-05,
      "loss": 0.1514,
      "step": 370
    },
    {
      "epoch": 1.7331812998859748,
      "grad_norm": 0.24707187712192535,
      "learning_rate": 2.254543861391121e-05,
      "loss": 0.1391,
      "step": 380
    },
    {
      "epoch": 1.7787913340935004,
      "grad_norm": 0.32328999042510986,
      "learning_rate": 2.1227018379854383e-05,
      "loss": 0.1586,
      "step": 390
    },
    {
      "epoch": 1.824401368301026,
      "grad_norm": 0.3262864649295807,
      "learning_rate": 1.991925691861241e-05,
      "loss": 0.1512,
      "step": 400
    },
    {
      "epoch": 1.870011402508552,
      "grad_norm": 0.2703591287136078,
      "learning_rate": 1.8625848690883686e-05,
      "loss": 0.1463,
      "step": 410
    },
    {
      "epoch": 1.9156214367160775,
      "grad_norm": 0.2998369336128235,
      "learning_rate": 1.735044760910251e-05,
      "loss": 0.1534,
      "step": 420
    },
    {
      "epoch": 1.9612314709236032,
      "grad_norm": 0.24344561994075775,
      "learning_rate": 1.609665671503987e-05,
      "loss": 0.1475,
      "step": 430
    },
    {
      "epoch": 2.006841505131129,
      "grad_norm": 0.32751208543777466,
      "learning_rate": 1.4868018001115166e-05,
      "loss": 0.1484,
      "step": 440
    },
    {
      "epoch": 2.0524515393386547,
      "grad_norm": 0.20572128891944885,
      "learning_rate": 1.3668002404174047e-05,
      "loss": 0.1295,
      "step": 450
    },
    {
      "epoch": 2.0980615735461803,
      "grad_norm": 0.40092527866363525,
      "learning_rate": 1.2500000000000006e-05,
      "loss": 0.1264,
      "step": 460
    },
    {
      "epoch": 2.143671607753706,
      "grad_norm": 0.46149423718452454,
      "learning_rate": 1.136731042626073e-05,
      "loss": 0.1146,
      "step": 470
    },
    {
      "epoch": 2.1892816419612315,
      "grad_norm": 0.29774051904678345,
      "learning_rate": 1.027313356094443e-05,
      "loss": 0.1229,
      "step": 480
    },
    {
      "epoch": 2.234891676168757,
      "grad_norm": 0.292483925819397,
      "learning_rate": 9.220560482619956e-06,
      "loss": 0.1259,
      "step": 490
    },
    {
      "epoch": 2.280501710376283,
      "grad_norm": 0.2732001841068268,
      "learning_rate": 8.21256473805811e-06,
      "loss": 0.1219,
      "step": 500
    },
    {
      "epoch": 2.3261117445838084,
      "grad_norm": 0.22822120785713196,
      "learning_rate": 7.251993941883428e-06,
      "loss": 0.1275,
      "step": 510
    },
    {
      "epoch": 2.371721778791334,
      "grad_norm": 0.2730989456176758,
      "learning_rate": 6.3415617319875716e-06,
      "loss": 0.1117,
      "step": 520
    },
    {
      "epoch": 2.4173318129988597,
      "grad_norm": 0.3378787636756897,
      "learning_rate": 5.483840103430599e-06,
      "loss": 0.1197,
      "step": 530
    },
    {
      "epoch": 2.4629418472063853,
      "grad_norm": 0.2916674017906189,
      "learning_rate": 4.681252142486841e-06,
      "loss": 0.1184,
      "step": 540
    },
    {
      "epoch": 2.508551881413911,
      "grad_norm": 0.325039803981781,
      "learning_rate": 3.936065181362211e-06,
      "loss": 0.1304,
      "step": 550
    },
    {
      "epoch": 2.5541619156214366,
      "grad_norm": 0.3215184509754181,
      "learning_rate": 3.2503843929207413e-06,
      "loss": 0.1203,
      "step": 560
    },
    {
      "epoch": 2.5997719498289626,
      "grad_norm": 0.2537631094455719,
      "learning_rate": 2.6261468435155978e-06,
      "loss": 0.1193,
      "step": 570
    },
    {
      "epoch": 2.6453819840364883,
      "grad_norm": 0.3343857526779175,
      "learning_rate": 2.065116020725433e-06,
      "loss": 0.126,
      "step": 580
    },
    {
      "epoch": 2.690992018244014,
      "grad_norm": 0.3588564693927765,
      "learning_rate": 1.5688768514553587e-06,
      "loss": 0.1254,
      "step": 590
    },
    {
      "epoch": 2.7366020524515395,
      "grad_norm": 0.2771284282207489,
      "learning_rate": 1.138831224476533e-06,
      "loss": 0.1185,
      "step": 600
    },
    {
      "epoch": 2.782212086659065,
      "grad_norm": 0.28164076805114746,
      "learning_rate": 7.761940300533399e-07,
      "loss": 0.1265,
      "step": 610
    },
    {
      "epoch": 2.827822120866591,
      "grad_norm": 0.31134212017059326,
      "learning_rate": 4.819897278462521e-07,
      "loss": 0.1174,
      "step": 620
    },
    {
      "epoch": 2.8734321550741164,
      "grad_norm": 0.3330036997795105,
      "learning_rate": 2.5704945278623436e-07,
      "loss": 0.1293,
      "step": 630
    },
    {
      "epoch": 2.919042189281642,
      "grad_norm": 0.2838246822357178,
      "learning_rate": 1.0200866709657864e-07,
      "loss": 0.1214,
      "step": 640
    },
    {
      "epoch": 2.9646522234891677,
      "grad_norm": 0.3268677592277527,
      "learning_rate": 1.730536509532421e-08,
      "loss": 0.1177,
      "step": 650
    }
  ],
  "logging_steps": 10,
  "max_steps": 657,
  "num_input_tokens_seen": 0,
  "num_train_epochs": 3,
  "save_steps": 500,
  "stateful_callbacks": {
    "TrainerControl": {
      "args": {
        "should_epoch_stop": false,
        "should_evaluate": false,
        "should_log": false,
        "should_save": true,
        "should_training_stop": true
      },
      "attributes": {}
    }
  },
  "total_flos": 1.1714560424463565e+17,
  "train_batch_size": 2,
  "trial_name": null,
  "trial_params": null
}
